census_pgeoloader.py
census_pgeoloader-0.2.0.dist-info/DESCRIPTION.rst
census_pgeoloader-0.2.0.dist-info/METADATA
census_pgeoloader-0.2.0.dist-info/RECORD
census_pgeoloader-0.2.0.dist-info/WHEEL
census_pgeoloader-0.2.0.dist-info/entry_points.txt
census_pgeoloader-0.2.0.dist-info/metadata.json
census_pgeoloader-0.2.0.dist-info/top_level.txt
