Metadata-Version: 2.0
Name: census-pgeoloader
Version: 0.2.0
Summary: Load Census shapefiles into PostGIS
Home-page: https://github.com/The-Politico/census_pgeoloader/
Author: Jon McClure
Author-email: jmcclure@politico.com
License: GPLv3
Platform: UNKNOWN
Classifier: Development Status :: 3 - Alpha
Classifier: Intended Audience :: Developers
Classifier: Intended Audience :: Science/Research
Classifier: License :: OSI Approved :: GNU General Public License v3 (GPLv3)
Classifier: Natural Language :: English
Classifier: Operating System :: OS Independent
Classifier: Programming Language :: Python
Classifier: Programming Language :: Python :: 2
Classifier: Programming Language :: Python :: 2.7
Classifier: Programming Language :: Python :: 3
Classifier: Programming Language :: Python :: 3.4
Classifier: Programming Language :: Python :: 3.5
Classifier: Programming Language :: Python :: 3.6
Classifier: Topic :: Sociology
Requires-Dist: click
Requires-Dist: idna
Requires-Dist: psycopg2
Requires-Dist: pyOpenSSL
Requires-Dist: requests
Requires-Dist: us
